gecosistema_win_service/__init__.py
gecosistema_win_service/example.py
gecosistema_win_service/winservice.py
gecosistema_win_service-0.0.25.dist-info/LICENSE
gecosistema_win_service-0.0.25.dist-info/METADATA
gecosistema_win_service-0.0.25.dist-info/WHEEL
gecosistema_win_service-0.0.25.dist-info/top_level.txt
gecosistema_win_service-0.0.25.dist-info/RECORD
